vcd_cli/__init__.py
vcd_cli/amqp.py
vcd_cli/ca_certificates.py
vcd_cli/catalog.py
vcd_cli/crl_certificates.py
vcd_cli/datastore.py
vcd_cli/dhcp_pool.py
vcd_cli/disk.py
vcd_cli/extension.py
vcd_cli/firewall_rule.py
vcd_cli/gateway.py
vcd_cli/info.py
vcd_cli/ipsec_vpn.py
vcd_cli/login.py
vcd_cli/nat_rule.py
vcd_cli/netpool.py
vcd_cli/network.py
vcd_cli/nsxt.py
vcd_cli/org.py
vcd_cli/plugin.py
vcd_cli/profile.py
vcd_cli/profiles.py
vcd_cli/pvdc.py
vcd_cli/right.py
vcd_cli/role.py
vcd_cli/routed.py
vcd_cli/search.py
vcd_cli/service_certificates.py
vcd_cli/static_route.py
vcd_cli/system.py
vcd_cli/task.py
vcd_cli/user.py
vcd_cli/utils.py
vcd_cli/vapp.py
vcd_cli/vapp_network.py
vcd_cli/vapp_network_dhcp.py
vcd_cli/vapp_network_firewall.py
vcd_cli/vapp_network_nat.py
vcd_cli/vapp_network_static_route.py
vcd_cli/vc.py
vcd_cli/vcd.py
vcd_cli/vdc.py
vcd_cli/vm.py
vcd_cli/browsercookie/__init__.py
vcd_cli-24.1.0.data/data/open_source_license_VMware_vCloud_Director_CLI_21.0.0_GA.txt
vcd_cli-24.1.0.dist-info/AUTHORS
vcd_cli-24.1.0.dist-info/LICENSE.txt
vcd_cli-24.1.0.dist-info/METADATA
vcd_cli-24.1.0.dist-info/NOTICE.txt
vcd_cli-24.1.0.dist-info/WHEEL
vcd_cli-24.1.0.dist-info/entry_points.txt
vcd_cli-24.1.0.dist-info/pbr.json
vcd_cli-24.1.0.dist-info/top_level.txt
vcd_cli-24.1.0.dist-info/RECORD
