Metadata-Version: 2.1
Name: vcd-cli
Version: 24.1.0
Summary: VMware vCloud Director CLI
Home-page: https://github.com/vmware/vcd-cli
Author: Paco Gomez
Author-email: pgomez@vmware.com
License: Apache 2
Platform: UNKNOWN
Classifier: Environment :: Console
Classifier: Intended Audience :: System Administrators
Classifier: Intended Audience :: Developers
Classifier: Operating System :: POSIX :: Linux
Classifier: Operating System :: MacOS :: MacOS X
Classifier: Operating System :: Microsoft :: Windows
Classifier: Programming Language :: Python
Classifier: Programming Language :: Python :: 3
Requires-Python: >=3
License-File: LICENSE.txt
License-File: NOTICE.txt
License-File: AUTHORS
Requires-Dist: click (>=7.0)
Requires-Dist: colorama (>=0.3.9)
Requires-Dist: keyring (<=23.5.0,>=19.0.0)
Requires-Dist: pycryptodome (<4.0.0,>=3.7.0)
Requires-Dist: pyvcloud (<24.0.0,>=23.0.1)
Requires-Dist: tabulate (>=0.7.5)
Requires-Dist: unittest-xml-reporting (>=2.2.1)
Requires-Dist: pypiwin32 (>=223) ; (platform_system=="Windows")
